MANIFEST.in
README.rst
setup.py
bin/wadus
wadus/__init__.py
wadus/aws_amis.py
wadus/aws_balancers.py
wadus/aws_instances.py
wadus/aws_sts.py
wadus.egg-info/PKG-INFO
wadus.egg-info/SOURCES.txt
wadus.egg-info/dependency_links.txt
wadus.egg-info/not-zip-safe
wadus.egg-info/requires.txt
wadus.egg-info/top_level.txt