Metadata-Version: 1.0
Name: wadus
Version: 0.3
Summary: Cloud basic tool
Home-page: http://github.com/jesus-sayar/wadus
Author: Jesus Sayar
Author-email: sayar.jesus@gmail.com
License: MIT
Keywords: wadus DevOps sysadmin cloud aws
Platform: UNKNOWN
